{"budget":[{"name":"category_other","icon":"category_other","num":0},{"name":"category_clothes","icon":"category_clothes","num":0},{"name":"category_communication","icon":"category_communication","num":0},{"name":"category_education","icon":"category_education","num":0},{"name":"category_food","icon":"category_food","num":0},{"name":"category_fruit","icon":"category_fruit","num":0},{"name":"category_gift","icon":"category_gift","num":0},{"name":"category_house","icon":"category_house","num":0},{"name":"category_jewelry","icon":"category_jewelry","num":0},{"name":"category_traffic","icon":"category_traffic","num":0}]}